apk2java/__init__.py
apk2java/java/Class2Java.jar
apk2java/java/jd-core-1.1.3.jar
apk2java/tools/dex-tools/dex-tools-2.1-SNAPSHOT/LICENSE.txt
apk2java/tools/dex-tools/dex-tools-2.1-SNAPSHOT/NOTICE.txt
apk2java/tools/dex-tools/dex-tools-2.1-SNAPSHOT/d2j-apk-sign.bat
apk2java/tools/dex-tools/dex-tools-2.1-SNAPSHOT/d2j-apk-sign.sh
apk2java/tools/dex-tools/dex-tools-2.1-SNAPSHOT/d2j-asm-verify.bat
apk2java/tools/dex-tools/dex-tools-2.1-SNAPSHOT/d2j-asm-verify.sh
apk2java/tools/dex-tools/dex-tools-2.1-SNAPSHOT/d2j-baksmali.bat
apk2java/tools/dex-tools/dex-tools-2.1-SNAPSHOT/d2j-baksmali.sh
apk2java/tools/dex-tools/dex-tools-2.1-SNAPSHOT/d2j-class-version-switch.bat
apk2java/tools/dex-tools/dex-tools-2.1-SNAPSHOT/d2j-class-version-switch.sh
apk2java/tools/dex-tools/dex-tools-2.1-SNAPSHOT/d2j-decrypt-string.bat
apk2java/tools/dex-tools/dex-tools-2.1-SNAPSHOT/d2j-decrypt-string.sh
apk2java/tools/dex-tools/dex-tools-2.1-SNAPSHOT/d2j-dex-recompute-checksum.bat
apk2java/tools/dex-tools/dex-tools-2.1-SNAPSHOT/d2j-dex-recompute-checksum.sh
apk2java/tools/dex-tools/dex-tools-2.1-SNAPSHOT/d2j-dex-weaver.bat
apk2java/tools/dex-tools/dex-tools-2.1-SNAPSHOT/d2j-dex-weaver.sh
apk2java/tools/dex-tools/dex-tools-2.1-SNAPSHOT/d2j-dex2jar.bat
apk2java/tools/dex-tools/dex-tools-2.1-SNAPSHOT/d2j-dex2jar.sh
apk2java/tools/dex-tools/dex-tools-2.1-SNAPSHOT/d2j-dex2smali.bat
apk2java/tools/dex-tools/dex-tools-2.1-SNAPSHOT/d2j-dex2smali.sh
apk2java/tools/dex-tools/dex-tools-2.1-SNAPSHOT/d2j-jar-access.bat
apk2java/tools/dex-tools/dex-tools-2.1-SNAPSHOT/d2j-jar-access.sh
apk2java/tools/dex-tools/dex-tools-2.1-SNAPSHOT/d2j-jar-weaver.bat
apk2java/tools/dex-tools/dex-tools-2.1-SNAPSHOT/d2j-jar-weaver.sh
apk2java/tools/dex-tools/dex-tools-2.1-SNAPSHOT/d2j-jar2dex.bat
apk2java/tools/dex-tools/dex-tools-2.1-SNAPSHOT/d2j-jar2dex.sh
apk2java/tools/dex-tools/dex-tools-2.1-SNAPSHOT/d2j-jar2jasmin.bat
apk2java/tools/dex-tools/dex-tools-2.1-SNAPSHOT/d2j-jar2jasmin.sh
apk2java-0.0.5.dist-info/LICENSE
apk2java-0.0.5.dist-info/METADATA
apk2java-0.0.5.dist-info/WHEEL
apk2java-0.0.5.dist-info/entry_points.txt
apk2java-0.0.5.dist-info/top_level.txt
apk2java-0.0.5.dist-info/RECORD
