Metadata-Version: 2.1
Name: apk2java
Version: 0.0.5
Summary: Decompile APK to Java
Home-page: https://ci-yow.com
Author: MadSquirrel
Author-email: benoit.forgette@ci-yow.com
License: UNKNOWN
Download-URL: https://gitlab.com/MadSquirrels/mobile/apk2java
Platform: UNKNOWN
Classifier: Programming Language :: Python :: 3
Classifier: Development Status :: 1 - Planning
Requires-Python: >=3.5
